{
	"inputs" : 
	[
		{
			"path" : "CMakeLists.txt"
		},
		{
			"isGenerated" : true,
			"path" : "build/CMakeFiles/3.29.2/CMakeSystem.cmake"
		},
		{
			"isCMake" : true,
			"isExternal" : true,
			"path" : "/usr/local/Cellar/cmake/3.29.2/share/cmake/Modules/CMakeSystemSpecificInitialize.cmake"
		},
		{
			"isCMake" : true,
			"isExternal" : true,
			"path" : "/usr/local/Cellar/cmake/3.29.2/share/cmake/Modules/Platform/Darwin-Initialize.cmake"
		},
		{
			"isGenerated" : true,
			"path" : "build/CMakeFiles/3.29.2/CMakeCCompiler.cmake"
		},
		{
			"isGenerated" : true,
			"path" : "build/CMakeFiles/3.29.2/CMakeCXXCompiler.cmake"
		},
		{
			"isCMake" : true,
			"isExternal" : true,
			"path" : "/usr/local/Cellar/cmake/3.29.2/share/cmake/Modules/CMakeSystemSpecificInformation.cmake"
		},
		{
			"isCMake" : true,
			"isExternal" : true,
			"path" : "/usr/local/Cellar/cmake/3.29.2/share/cmake/Modules/CMakeGenericSystem.cmake"
		},
		{
			"isCMake" : true,
			"isExternal" : true,
			"path" : "/usr/local/Cellar/cmake/3.29.2/share/cmake/Modules/CMakeInitializeConfigs.cmake"
		},
		{
			"isCMake" : true,
			"isExternal" : true,
			"path" : "/usr/local/Cellar/cmake/3.29.2/share/cmake/Modules/Platform/Darwin.cmake"
		},
		{
			"isCMake" : true,
			"isExternal" : true,
			"path" : "/usr/local/Cellar/cmake/3.29.2/share/cmake/Modules/Platform/UnixPaths.cmake"
		},
		{
			"isCMake" : true,
			"isExternal" : true,
			"path" : "/usr/local/Cellar/cmake/3.29.2/share/cmake/Modules/CMakeCInformation.cmake"
		},
		{
			"isCMake" : true,
			"isExternal" : true,
			"path" : "/usr/local/Cellar/cmake/3.29.2/share/cmake/Modules/CMakeLanguageInformation.cmake"
		},
		{
			"isCMake" : true,
			"isExternal" : true,
			"path" : "/usr/local/Cellar/cmake/3.29.2/share/cmake/Modules/Compiler/AppleClang-C.cmake"
		},
		{
			"isCMake" : true,
			"isExternal" : true,
			"path" : "/usr/local/Cellar/cmake/3.29.2/share/cmake/Modules/Compiler/Clang.cmake"
		},
		{
			"isCMake" : true,
			"isExternal" : true,
			"path" : "/usr/local/Cellar/cmake/3.29.2/share/cmake/Modules/Compiler/CMakeCommonCompilerMacros.cmake"
		},
		{
			"isCMake" : true,
			"isExternal" : true,
			"path" : "/usr/local/Cellar/cmake/3.29.2/share/cmake/Modules/Compiler/GNU.cmake"
		},
		{
			"isCMake" : true,
			"isExternal" : true,
			"path" : "/usr/local/Cellar/cmake/3.29.2/share/cmake/Modules/Compiler/CMakeCommonCompilerMacros.cmake"
		},
		{
			"isCMake" : true,
			"isExternal" : true,
			"path" : "/usr/local/Cellar/cmake/3.29.2/share/cmake/Modules/Platform/Apple-AppleClang-C.cmake"
		},
		{
			"isCMake" : true,
			"isExternal" : true,
			"path" : "/usr/local/Cellar/cmake/3.29.2/share/cmake/Modules/Platform/Apple-Clang-C.cmake"
		},
		{
			"isCMake" : true,
			"isExternal" : true,
			"path" : "/usr/local/Cellar/cmake/3.29.2/share/cmake/Modules/Platform/Apple-Clang.cmake"
		},
		{
			"isCMake" : true,
			"isExternal" : true,
			"path" : "/usr/local/Cellar/cmake/3.29.2/share/cmake/Modules/CMakeCommonLanguageInclude.cmake"
		},
		{
			"isCMake" : true,
			"isExternal" : true,
			"path" : "/usr/local/Cellar/cmake/3.29.2/share/cmake/Modules/CMakeCXXInformation.cmake"
		},
		{
			"isCMake" : true,
			"isExternal" : true,
			"path" : "/usr/local/Cellar/cmake/3.29.2/share/cmake/Modules/CMakeLanguageInformation.cmake"
		},
		{
			"isCMake" : true,
			"isExternal" : true,
			"path" : "/usr/local/Cellar/cmake/3.29.2/share/cmake/Modules/Compiler/AppleClang-CXX.cmake"
		},
		{
			"isCMake" : true,
			"isExternal" : true,
			"path" : "/usr/local/Cellar/cmake/3.29.2/share/cmake/Modules/Compiler/Clang.cmake"
		},
		{
			"isCMake" : true,
			"isExternal" : true,
			"path" : "/usr/local/Cellar/cmake/3.29.2/share/cmake/Modules/Platform/Apple-AppleClang-CXX.cmake"
		},
		{
			"isCMake" : true,
			"isExternal" : true,
			"path" : "/usr/local/Cellar/cmake/3.29.2/share/cmake/Modules/Platform/Apple-Clang-CXX.cmake"
		},
		{
			"isCMake" : true,
			"isExternal" : true,
			"path" : "/usr/local/Cellar/cmake/3.29.2/share/cmake/Modules/Platform/Apple-Clang.cmake"
		},
		{
			"isCMake" : true,
			"isExternal" : true,
			"path" : "/usr/local/Cellar/cmake/3.29.2/share/cmake/Modules/CMakeCommonLanguageInclude.cmake"
		},
		{
			"path" : "glad/CMakeLists.txt"
		},
		{
			"path" : "glfw/CMakeLists.txt"
		},
		{
			"isCMake" : true,
			"isExternal" : true,
			"path" : "/usr/local/Cellar/cmake/3.29.2/share/cmake/Modules/GNUInstallDirs.cmake"
		},
		{
			"isCMake" : true,
			"isExternal" : true,
			"path" : "/usr/local/Cellar/cmake/3.29.2/share/cmake/Modules/CMakeDependentOption.cmake"
		},
		{
			"isCMake" : true,
			"isExternal" : true,
			"path" : "/usr/local/Cellar/cmake/3.29.2/share/cmake/Modules/FindThreads.cmake"
		},
		{
			"isCMake" : true,
			"isExternal" : true,
			"path" : "/usr/local/Cellar/cmake/3.29.2/share/cmake/Modules/CheckLibraryExists.cmake"
		},
		{
			"isCMake" : true,
			"isExternal" : true,
			"path" : "/usr/local/Cellar/cmake/3.29.2/share/cmake/Modules/CheckIncludeFile.cmake"
		},
		{
			"isCMake" : true,
			"isExternal" : true,
			"path" : "/usr/local/Cellar/cmake/3.29.2/share/cmake/Modules/CheckCSourceCompiles.cmake"
		},
		{
			"isCMake" : true,
			"isExternal" : true,
			"path" : "/usr/local/Cellar/cmake/3.29.2/share/cmake/Modules/Internal/CheckSourceCompiles.cmake"
		},
		{
			"isCMake" : true,
			"isExternal" : true,
			"path" : "/usr/local/Cellar/cmake/3.29.2/share/cmake/Modules/FindPackageHandleStandardArgs.cmake"
		},
		{
			"isCMake" : true,
			"isExternal" : true,
			"path" : "/usr/local/Cellar/cmake/3.29.2/share/cmake/Modules/FindPackageMessage.cmake"
		},
		{
			"isCMake" : true,
			"isExternal" : true,
			"path" : "/usr/local/Cellar/cmake/3.29.2/share/cmake/Modules/CMakePackageConfigHelpers.cmake"
		},
		{
			"isCMake" : true,
			"isExternal" : true,
			"path" : "/usr/local/Cellar/cmake/3.29.2/share/cmake/Modules/WriteBasicConfigVersionFile.cmake"
		},
		{
			"path" : "glfw/CMake/glfw3Config.cmake.in"
		},
		{
			"isCMake" : true,
			"isExternal" : true,
			"path" : "/usr/local/Cellar/cmake/3.29.2/share/cmake/Modules/BasicConfigVersion-SameMajorVersion.cmake.in"
		},
		{
			"path" : "glfw/CMake/cmake_uninstall.cmake.in"
		},
		{
			"path" : "glfw/src/CMakeLists.txt"
		},
		{
			"path" : "glfw/CMake/glfw3.pc.in"
		},
		{
			"path" : "glfw/docs/CMakeLists.txt"
		},
		{
			"isCMake" : true,
			"isExternal" : true,
			"path" : "/usr/local/Cellar/cmake/3.29.2/share/cmake/Modules/FindDoxygen.cmake"
		},
		{
			"isCMake" : true,
			"isExternal" : true,
			"path" : "/usr/local/Cellar/cmake/3.29.2/share/cmake/Modules/FindPackageHandleStandardArgs.cmake"
		},
		{
			"isCMake" : true,
			"isExternal" : true,
			"path" : "/usr/local/Cellar/cmake/3.29.2/share/cmake/Modules/FindPackageMessage.cmake"
		},
		{
			"path" : "glm/CMakeLists.txt"
		},
		{
			"isCMake" : true,
			"isExternal" : true,
			"path" : "/usr/local/Cellar/cmake/3.29.2/share/cmake/Modules/GNUInstallDirs.cmake"
		},
		{
			"isCMake" : true,
			"isExternal" : true,
			"path" : "/usr/local/Cellar/cmake/3.29.2/share/cmake/Modules/CMakePackageConfigHelpers.cmake"
		},
		{
			"isCMake" : true,
			"isExternal" : true,
			"path" : "/usr/local/Cellar/cmake/3.29.2/share/cmake/Modules/WriteBasicConfigVersionFile.cmake"
		},
		{
			"isCMake" : true,
			"isExternal" : true,
			"path" : "/usr/local/Cellar/cmake/3.29.2/share/cmake/Modules/BasicConfigVersion-AnyNewerVersion.cmake.in"
		},
		{
			"path" : "glm/cmake/glmBuildConfig.cmake.in"
		},
		{
			"path" : "glm/cmake/glmConfig.cmake.in"
		},
		{
			"path" : "glm/cmake/glm.pc.in"
		},
		{
			"path" : "glm/glm/CMakeLists.txt"
		},
		{
			"path" : "glm/test/CMakeLists.txt"
		},
		{
			"path" : "glm/test/bug/CMakeLists.txt"
		},
		{
			"path" : "glm/test/core/CMakeLists.txt"
		},
		{
			"path" : "glm/test/gtc/CMakeLists.txt"
		},
		{
			"path" : "glm/test/gtx/CMakeLists.txt"
		},
		{
			"path" : "src/CMakeLists.txt"
		}
	],
	"kind" : "cmakeFiles",
	"paths" : 
	{
		"build" : "/Users/bearkun/Desktop/codes/Cpp/OpenGL/build",
		"source" : "/Users/bearkun/Desktop/codes/Cpp/OpenGL"
	},
	"version" : 
	{
		"major" : 1,
		"minor" : 0
	}
}
